argus_dynamixel/__init__.py
argus_dynamixel/argus_dynamixel.py
argus_dynamixel-0.1.6.dist-info/LICENSE
argus_dynamixel-0.1.6.dist-info/METADATA
argus_dynamixel-0.1.6.dist-info/WHEEL
argus_dynamixel-0.1.6.dist-info/RECORD
