Metadata-Version: 2.1
Name: argus_dynamixel
Version: 0.1.6
Summary: 
Author: Alan Vasquez
Requires-Python: >=3.10,<4.0
Classifier: Programming Language :: Python :: 3
Classifier: Programming Language :: Python :: 3.10
Classifier: Programming Language :: Python :: 3.11
Classifier: Programming Language :: Python :: 3.12
Requires-Dist: dynamixel-sdk (>=3.7.31,<4.0.0)
Requires-Dist: python-dotenv (>=1.0.1)
